{
  "id": "quick-start/part4-operations",
  "title": "Часть 4. Основные операции: Закупки, отгрузки и оплаты",
  "description": "Теперь, когда товары, клиенты и поставщики добавлены, можно переходить к ежедневной работе в системе. В этом разделе вы узнаете, как:",
  "source": "@site/docs/quick-start/part4-operations.md",
  "sourceDirName": "quick-start",
  "slug": "/quick-start/part4-operations",
  "permalink": "/docs/quick-start/part4-operations",
  "draft": false,
  "unlisted": false,
  "tags": [],
  "version": "current",
  "sidebarPosition": 5,
  "frontMatter": {
    "id": "part4-operations",
    "title": "Часть 4. Основные операции: Закупки, отгрузки и оплаты",
    "sidebar_label": "Часть 4: Закупки, отгрузки и оплаты",
    "sidebar_position": 5
  },
  "sidebar": "tutorialSidebar",
  "previous": {
    "title": "Часть 3: Клиенты, поставщики и балансы",
    "permalink": "/docs/quick-start/part3-finance"
  },
  "next": {
    "title": "Часть 5: Работа с отчетностью",
    "permalink": "/docs/quick-start/part5-reports"
  }
}